.bumpversion.cfg
.gitignore
MANIFEST.in
Makefile
README.md
pypackage.mk
requirements.txt
setup.py
shippable.yml
.circleci/config.yml
docs/.gitignore
docs/compile_website_from_scratch.sh
docs/sphinxtogithub.py
docs/source/api.rst.inc
docs/source/api_reference.rst
docs/source/changelog.rst
docs/source/conf.py
docs/source/credits.rst
docs/source/definitions.txt
docs/source/download.html
docs/source/fork.html
docs/source/index.rst
docs/source/my_static/.empty
docs/source/my_templates/layout.html
src/ConfTools.egg-info/PKG-INFO
src/ConfTools.egg-info/SOURCES.txt
src/ConfTools.egg-info/dependency_links.txt
src/ConfTools.egg-info/requires.txt
src/ConfTools.egg-info/top_level.txt
src/conf_tools/__init__.py
src/conf_tools/checks.py
src/conf_tools/code_desc.py
src/conf_tools/code_specs.py
src/conf_tools/exceptions.py
src/conf_tools/global_config.py
src/conf_tools/instantiate_utils.py
src/conf_tools/load_entries.py
src/conf_tools/master.py
src/conf_tools/objspec.py
src/conf_tools/patterns.py
src/conf_tools/special_subst.py
src/conf_tools/valid.py
src/conf_tools/unittests/__init__.py
src/conf_tools/unittests/pickling_test.py
src/conf_tools/unittests/utils.py
src/conf_tools/unittests/wildcards_test.py
src/conf_tools/unittests/groups/__init__.py
src/conf_tools/unittests/groups/groups_test.py
src/conf_tools/unittests/instantiate_tests/__init__.py
src/conf_tools/unittests/instantiate_tests/static_test.py
src/conf_tools/unittests/templating/__init__.py
src/conf_tools/unittests/templating/other_tests.py
src/conf_tools/unittests/templating/simple_use_tests.py
src/conf_tools/utils/__init__.py
src/conf_tools/utils/col_logging.py
src/conf_tools/utils/expansion.py
src/conf_tools/utils/friendly_paths.py
src/conf_tools/utils/indent_string.py
src/conf_tools/utils/locate_files_imp.py
src/conf_tools/utils/not_found.py
src/conf_tools/utils/pickling.py
src/conf_tools/utils/resources.py
src/conf_tools/utils/term_color.py
src/conf_tools/utils/terminal_size.py
src/conf_tools/utils/wildcards.py