Metadata-Version: 1.1
Name: ConfTools
Version: 1.9.8
Summary: UNKNOWN
Home-page: http://github.com/AndreaCensi/conf_tools/
Author: Andrea Censi
Author-email: censi@mit.edu
License: LGPL
Download-URL: http://github.com/AndreaCensi/conf_tools/tarball/1.9.8
Keywords: configuration
Platform: UNKNOWN
Classifier: Development Status :: 4 - Beta
